{
  "resort_name": "Disney's Polynesian Villas \u0026 Bungalows (including the new Island Tower addition)",
  "resort_code": "POLYV",
  "year": 2027,
  "columns": [
    {
      "room_type": "DELUXE STUDIO",
      "view": "R",
      "sleeps": 5
    },
    {
      "room_type": "DELUXE STUDIO",
      "view": "P",
      "sleeps": 5
    },
    {
      "room_type": "TWO-BEDROOM VILLA",
      "view": "P",
      "sleeps": 9
    },
    {
      "room_type": "TWO-BEDROOM VILLA",
      "view": "R",
      "sleeps": 9
    },
    {
      "room_type": "DUO STUDIO",
      "view": "P",
      "sleeps": 2
    },
    {
      "room_type": "DUO STUDIO",
      "view": "PM",
      "sleeps": 2
    },
    {
      "room_type": "DUO STUDIO",
      "view": "R",
      "sleeps": 2
    },
    {
      "room_type": "DELUXE STUDIO",
      "view": "P",
      "sleeps": 5
    },
    {
      "room_type": "DELUXE STUDIO",
      "view": "TP",
      "sleeps": 5
    },
    {
      "room_type": "DELUXE STUDIO",
      "view": "R",
      "sleeps": 5
    },
    {
      "room_type": "ONE-BEDROOM VILLA",
      "view": "P",
      "sleeps": 5
    },
    {
      "room_type": "ONE-BEDROOM VILLA",
      "view": "TP",
      "sleeps": 5
    },
    {
      "room_type": "ONE-BEDROOM VILLA",
      "view": "R",
      "sleeps": 5
    },
    {
      "room_type": "TWO-BEDROOM VILLA",
      "view": "P",
      "sleeps": 9
    },
    {
      "room_type": "TWO-BEDROOM VILLA",
      "view": "TP",
      "sleeps": 9
    },
    {
      "room_type": "TWO-BEDROOM VILLA",
      "view": "P",
      "sleeps": 9
    },
    {
      "room_type": "TWO-BEDROOM VILLA",
      "view": "TP",
      "sleeps": 9
    }
  ],
  "seasons": [
    {
      "periods": [
        {
          "start": "2027-09-01",
          "end": "2027-09-30"
        }
      ],
      "sun_thu": [
        15,
        20,
        114,
        13,
        17,
        20,
        15,
        20,
        25,
        30,
        39,
        44,
        46,
        56,
        70,
        88,
        110
      ],
      "fri_sat": [
        18,
        24,
        134,
        15,
        20,
        24,
        18,
        24,
        30,
        36,
        47,
        53,
        55,
        67,
        81,
        105,
        129
      ]
    },
    {
      "periods": [
        {
          "start": "2027-01-01",
          "end": "2027-01-31"
        },
        {
          "start": "2027-05-01",
          "end": "2027-05-14"
        }
      ],
      "sun_thu": [
        17,
        22,
        122,
        14,
        18,
        21,
        17,
        22,
        26,
        34,
        42,
        47,
        49,
        61,
        72,
        96,
        118
      ],
      "fri_sat": [
        20,
        24,
        140,
        16,
        20,
        24,
        20,
        24,
        30,
        40,
        48,
        54,
        57,
        69,
        85,
        113,
        136
      ]
    },
    {
      "periods": [
        {
          "start": "2027-05-15",
          "end": "2027-06-10"
        },
        {
          "start": "2027-12-01",
          "end": "2027-12-23"
        }
      ],
      "sun_thu": [
        19,
        22,
        128,
        16,
        19,
        22,
        19,
        22,
        27,
        38,
        47,
        53,
        54,
        62,
        76,
        102,
        122
      ],
      "fri_sat": [
        22,
        26,
        147,
        18,
        21,
        26,
        22,
        26,
        32,
        44,
        52,
        61,
        62,
        73,
        90,
        119,
        144
      ]
    },
    {
      "periods": [
        {
          "start": "2027-02-01",
          "end": "2027-02-15"
        },
        {
          "start": "2027-06-11",
          "end": "2027-08-31"
        }
      ],
      "sun_thu": [
        20,
        24,
        136,
        17,
        20,
        24,
        20,
        24,
        29,
        40,
        48,
        54,
        56,
        68,
        82,
        108,
        128
      ],
      "fri_sat": [
        23,
        27,
        157,
        19,
        22,
        27,
        23,
        27,
        33,
        46,
        54,
        63,
        65,
        79,
        96,
        122,
        152
      ]
    },
    {
      "periods": [
        {
          "start": "2027-10-01",
          "end": "2027-11-23"
        },
        {
          "start": "2027-11-27",
          "end": "2027-11-30"
        }
      ],
      "sun_thu": [
        22,
        25,
        150,
        18,
        21,
        26,
        22,
        25,
        31,
        44,
        53,
        58,
        62,
        73,
        90,
        115,
        140
      ],
      "fri_sat": [
        25,
        30,
        172,
        20,
        24,
        29,
        25,
        30,
        36,
        50,
        60,
        67,
        70,
        84,
        101,
        132,
        162
      ]
    },
    {
      "periods": [
        {
          "start": "2027-02-16",
          "end": "2027-03-20"
        },
        {
          "start": "2027-03-29",
          "end": "2027-04-30"
        },
        {
          "start": "2027-11-24",
          "end": "2027-11-26"
        }
      ],
      "sun_thu": [
        25,
        28,
        162,
        20,
        23,
        28,
        25,
        28,
        34,
        48,
        54,
        65,
        68,
        79,
        96,
        126,
        153
      ],
      "fri_sat": [
        28,
        32,
        185,
        23,
        26,
        32,
        28,
        32,
        39,
        56,
        64,
        75,
        79,
        90,
        110,
        144,
        179
      ]
    },
    {
      "periods": [
        {
          "start": "2027-03-21",
          "end": "2027-03-28"
        },
        {
          "start": "2027-12-24",
          "end": "2027-12-31"
        }
      ],
      "sun_thu": [
        34,
        41,
        199,
        27,
        32,
        39,
        34,
        41,
        48,
        68,
        78,
        89,
        92,
        109,
        128,
        178,
        197
      ],
      "fri_sat": [
        36,
        43,
        226,
        30,
        36,
        43,
        36,
        43,
        53,
        78,
        86,
        98,
        105,
        125,
        149,
        198,
        226
      ]
    }
  ]
}